TransIpRestfullAPI/__init__.py
TransIpRestfullAPI/api.py
TransIpRestfullAPI/HttpLogic/Authenticate.py
TransIpRestfullAPI/HttpLogic/Exceptions.py
TransIpRestfullAPI/HttpLogic/RequestTypes.py
TransIpRestfullAPI/HttpLogic/__init__.py
TransIpRestfullAPI/Models/AvailabilityZone.py
TransIpRestfullAPI/Models/Branding.py
TransIpRestfullAPI/Models/Contacts.py
TransIpRestfullAPI/Models/DNSes.py
TransIpRestfullAPI/Models/Domain.py
TransIpRestfullAPI/Models/Invoice.py
TransIpRestfullAPI/Models/NameServers.py
TransIpRestfullAPI/Models/Products.py
TransIpRestfullAPI/Models/SSL.py
TransIpRestfullAPI/Models/__init__.py
TransIp_Restfull_API-0.1.2.dist-info/LICENSE
TransIp_Restfull_API-0.1.2.dist-info/METADATA
TransIp_Restfull_API-0.1.2.dist-info/WHEEL
TransIp_Restfull_API-0.1.2.dist-info/top_level.txt
TransIp_Restfull_API-0.1.2.dist-info/RECORD
