Metadata-Version: 2.1
Name: TransIp-Restfull-API
Version: 0.1.2
Summary: A python package to connect to the TransIp restfull API
Home-page: https://github.com/mathijswesterhof/TransIp_Rest_api_python
Author: Mathijs Westerhof
Author-email: author@example.com
License: UNKNOWN
Platform: UNKNOWN
Classifier: Programming Language :: Python :: 3
Classifier: License :: OSI Approved :: GNU General Public License v3 or later (GPLv3+)
Classifier: Operating System :: OS Independent
Requires-Python: >=3.6
